MANIFEST.in
README.md
README.rst
requirements.txt
setup.cfg
setup.py
ezds.egg-info/PKG-INFO
ezds.egg-info/SOURCES.txt
ezds.egg-info/dependency_links.txt
ezds.egg-info/requires.txt
ezds.egg-info/top_level.txt
pyds/__init__.py
pyds/cleaning.py
pyds/constants.py
pyds/evaluation.py
pyds/exploration.py
pyds/features_engineering.py
pyds/ingestion.py
pyds/ml.py
pyds/nlp.py
pyds/pipeline.py
pyds/transformations.py