Metadata-Version: 1.1
Name: ezds
Version: 1.0.0
Summary: data science made easy
Home-page: https://github.com/talperetz/pyds
Author: Tal Peretz
Author-email: talperetz24@gmail.com
License: BSD
Download-URL: https://github.com/talperetz/pyds/tarball/1.0.0
Platform: UNKNOWN
Classifier: Development Status :: 3 - Alpha
Classifier: Intended Audience :: Developers
Classifier: Programming Language :: Python :: 3
